drucker_client/__init__.py
drucker_client/_project.py
drucker_client/_version.py
drucker_client/drucker_worker_client.py
drucker_client/logger/__init__.py
drucker_client/logger/logger_fluent.py
drucker_client/logger/logger_interface.py
drucker_client/logger/logger_jsonlogger.py
drucker_client/protobuf/__init__.py
drucker_client/protobuf/drucker_pb2.py
drucker_client/protobuf/drucker_pb2_grpc.py
drucker_client-0.4.5.dist-info/LICENSE
drucker_client-0.4.5.dist-info/METADATA
drucker_client-0.4.5.dist-info/WHEEL
drucker_client-0.4.5.dist-info/top_level.txt
drucker_client-0.4.5.dist-info/RECORD
