Metadata-Version: 2.1
Name: drucker-client
Version: 0.4.5
Summary: A Python gRPC client for Drucker.
Home-page: https://github.com/drucker/drucker-client
Author: Drucker team and contributors
Author-email: drucker.developers@gmail.com
License: Apache License Version 2.0
Keywords: Drucker,Kubernetes,Python client,gRPC
Platform: UNKNOWN
Classifier: Development Status :: 3 - Alpha
Classifier: Environment :: Web Environment
Classifier: Topic :: Software Development :: Libraries :: Application Frameworks
Classifier: Intended Audience :: Developers
Classifier: Intended Audience :: Information Technology
Classifier: License :: OSI Approved :: Apache Software License
Classifier: Operating System :: OS Independent
Classifier: Programming Language :: Python
Classifier: Programming Language :: Python :: 3
Classifier: Programming Language :: Python :: 3.6
Classifier: Programming Language :: Python :: 3.7
Requires-Dist: grpcio (>=1.13.0)
Requires-Dist: grpcio-tools (>=1.13.0)
Requires-Dist: fluent-logger (>=0.9.3)
Requires-Dist: python-json-logger (>=0.1.9)
